[
  {
    "juz": {
      "id": "27"
    },
    "surah": {
      "id": "53"
    },
    "ayatNumber": "8",
    "arabicText": "ثُمَّ دَنَا فَتَدَلَّىٰ",
    "urduTranslationText": "",
    "englishTranslationText": "Then\tthe\tSpectacle\tbecame\tcloser,\tand\t\n(he)\tcame\tdown\tfully.\t\t",
    "romanUrduTranslationText": "Phir\twoh\tjalwa\tnazdeek\thuwa\t"
  },
  {
    "juz": {
      "id": "27"
    },
    "surah": {
      "id": "53"
    },
    "ayatNumber": "9",
    "arabicText": "فَكَانَ قَابَ قَوْسَيْنِ أَوْ أَدْنَىٰ",
    "urduTranslationText": "",
    "englishTranslationText": "So\tthe\tdistance\tbetween\tthe\tSpectacle\tand\t\nthe\tbeloved\twas\tonly\ttwo\tarms’\tlength,\tor\t\neven\tless.\t(The Heavenly Journey of \nProphet Muhammad – peace and \nblessings be upon him – was with body \nand soul.) \t\t",
    "romanUrduTranslationText": "Phir\tkhoob\tutar\tāaya\tto\tus\tjalwe\taur\tus\t\nMehboob\tmeiñ\tdo\thāth\tka\tfāsla\traha\t\nbalke\tis\tse\tbhi\tkam\t\t\t"
  },
  {
    "juz": {
      "id": "27"
    },
    "surah": {
      "id": "53"
    },
    "ayatNumber": "10",
    "arabicText": "فَأَوْحَىٰٓ إِلَىٰ عَبْدِهِۦ مَآ أَوْحَىٰ",
    "urduTranslationText": "",
    "englishTranslationText": "So\tAllah\tdivinely\trevealed\tto\tHis\t\nbondman,\twhatever\tHe\tdivinely\trevealed.\t",
    "romanUrduTranslationText": "Ab\twaḥi\tfarmayi\tapne\tbande\tko\tjo\twaḥi\t\nfarmayi\t"
  },
  {
    "juz": {
      "id": "27"
    },
    "surah": {
      "id": "53"
    },
    "ayatNumber": "11",
    "arabicText": "مَا كَذَبَ ٱلْفُؤَادُ مَا رَأَىٰٓ",
    "urduTranslationText": "",
    "englishTranslationText": "The\theart\tdid\tnot\tdeny,\twhat\tit\tsaw.\t(The Holy Prophet was bestowed with seeing Allah – see \nalso preceding verses 8,9, 10 .)\t\t",
    "romanUrduTranslationText": "Dil\tne\tjhoot\tna\tkahā\tjo\tdekha"
  },
  {
    "juz": {
      "id": "27"
    },
    "surah": {
      "id": "53"
    },
    "ayatNumber": "12",
    "arabicText": "أَفَتُمَـٰرُونَهُۥ عَلَىٰ مَا يَرَىٰ",
    "urduTranslationText": "",
    "englishTranslationText": "What!\tSo\tdo\tyou\tdispute\twith\thim\tregarding\twhat\the\tsaw?\t\t\t",
    "romanUrduTranslationText": "To\tkya\ttum\tun\tse\tunke\tdekhe\thuwe\tpar\t\njhagadte\tho\t"
  },
  {
    "juz": {
      "id": "27"
    },
    "surah": {
      "id": "53"
    },
    "ayatNumber": "13",
    "arabicText": "وَلَقَدْ رَءَاهُ نَزْلَةً أُخْرَىٰ",
    "urduTranslationText": "",
    "englishTranslationText": "And\tindeed\the\tdid\tsee\tthe\tSpectacle\tagain.\t\t",
    "romanUrduTranslationText": "Aur\tunhoñ\tne\tto\twoh\tjalwa\tdobār\tdekha\t"
  },
  {
    "juz": {
      "id": "27"
    },
    "surah": {
      "id": "53"
    },
    "ayatNumber": "14",
    "arabicText": "عِندَ سِدْرَةِ ٱلْمُنتَهَىٰ",
    "urduTranslationText": "",
    "englishTranslationText": "Near\tthe\tlote-tree\tof\tthe\tlast\tboundary.\t\t",
    "romanUrduTranslationText": "Sidra-tul\tMuntaha\tke\tpās"
  },
  {
    "juz": {
      "id": "27"
    },
    "surah": {
      "id": "53"
    },
    "ayatNumber": "15",
    "arabicText": "عِندَهَا جَنَّةُ ٱلْمَأْوَىٰٓ",
    "urduTranslationText": "",
    "englishTranslationText": "Close\tto\twhich\tis\tthe\tEverlasting\tParadise.\t\t\t\t",
    "romanUrduTranslationText": "Uske\tpās\tJannatul\tMāva\thai"
  },
  {
    "juz": {
      "id": "27"
    },
    "surah": {
      "id": "53"
    },
    "ayatNumber": "16",
    "arabicText": "إِذْ يَغْشَى ٱلسِّدْرَةَ مَا يَغْشَىٰ",
    "urduTranslationText": "",
    "englishTranslationText": "When\tthe\tlote-tree\twas\tbeing\tenveloped,\tby\twhatever\taround\tit.\t\t",
    "romanUrduTranslationText": "Jab\tSidra\tpar\tchha\traha\ttha\tjo\tchha\traha\ttha\t"
  },
  {
    "juz": {
      "id": "27"
    },
    "surah": {
      "id": "53"
    },
    "ayatNumber": "17",
    "arabicText": "مَا زَاغَ ٱلْبَصَرُ وَمَا طَغَىٰ",
    "urduTranslationText": "",
    "englishTranslationText": "The\tsight\tdid\tnot\tshift,\tnor\tdid\tit\tcross\tthe\tlimits.\t\t",
    "romanUrduTranslationText": "Āankh\tna\tkisi\ttaraf\tphiri\tna\thad\tse\tbadhi\t"
  },
  {
    "juz": {
      "id": "27"
    },
    "surah": {
      "id": "53"
    },
    "ayatNumber": "18",
    "arabicText": "لَقَدْ رَأَىٰ مِنْ ءَايَـٰتِ رَبِّهِ ٱلْكُبْرَىٰٓ",
    "urduTranslationText": "",
    "englishTranslationText": " Indeed\the\tsaw\tthe\tsupreme\tsigns\tof\this\tLord.\t",
    "romanUrduTranslationText": "Be-shak\tapne\tRab\tki\tbahut\tbadi\tnishāniyāñ\tdekhiñ\t"
  },
  {
    "juz": {
      "id": "27"
    },
    "surah": {
      "id": "53"
    },
    "ayatNumber": "19",
    "arabicText": "أَفَرَءَيْتُمُ ٱللَّـٰتَ وَٱلْعُزَّىٰ ",
    "urduTranslationText": "",
    "englishTranslationText": " So\tdid\tyou\tobserve\tthe\tidols\tLat\tand\tUzza?\t\t",
    "romanUrduTranslationText": " To\tkya\ttum\tne\tdekha\tLāt\taur\tUzza"
  },
  {
    "juz": {
      "id": "27"
    },
    "surah": {
      "id": "53"
    },
    "ayatNumber": "20",
    "arabicText": "وَمَنَوٰةَ ٱلثَّالِثَةَ ٱلْأُخْرَىٰٓ",
    "urduTranslationText": "",
    "englishTranslationText": " And\tsubsequently\tthe\tthird,\tthe\tManat?\t\t",
    "romanUrduTranslationText": "Aur\tus\tteesri\tmanāt\tko"
  },
  {
    "juz": {
      "id": "27"
    },
    "surah": {
      "id": "53"
    },
    "ayatNumber": "21",
    "arabicText": "أَلَكُمُ ٱلذَّكَرُ وَلَهُ ٱلْأُنثَىٰ ",
    "urduTranslationText": "",
    "englishTranslationText": "What!\tFor\tyou\tthe\tson,\tand\tfor\tHim\tthe\tdaughter?\t\t",
    "romanUrduTranslationText": "Kya\ttum\tko\tbeta\taur\tusko\tbeti"
  },
  {
    "juz": {
      "id": "27"
    },
    "surah": {
      "id": "53"
    },
    "ayatNumber": "22",
    "arabicText": "تِلْكَ إِذًۭا قِسْمَةٌۭ ضِيزَىٰٓ",
    "urduTranslationText": "",
    "englishTranslationText": "Then\tthat\tis\tsurely\ta\tvery\tunjust\tdistribution!\t\t\t",
    "romanUrduTranslationText": " Jab\tto\tyeh\tsakht\tbhoñdi\t(Buri)\ttaqseem\thai\t"
  },
  {
    "juz": {
      "id": "27"
    },
    "surah": {
      "id": "53"
    },
    "ayatNumber": "23",
    "arabicText": "إِنْ هِىَ إِلَّآ أَسْمَآءٌۭ سَمَّيْتُمُوهَآ أَنتُمْ وَءَابَآؤُكُم مَّآ أَنزَلَ ٱللَّهُ بِهَا مِن سُلْطَـٰنٍ ۚ إِن يَتَّبِعُونَ إِلَّا ٱلظَّنَّ وَمَا تَهْوَى ٱلْأَنفُسُ ۖ وَلَقَدْ جَآءَهُم مِّن رَّبِّهِمُ ٱلْهُدَىٰٓ",
    "urduTranslationText": "",
    "englishTranslationText": "They\tare\tnothing\tbut\tsome\tnames\tthat\tyou\thave\tcoined,\tyou\tand\tyour\tforefathers\t-\tAllah\thas\t\nnot\tsent\tany\tproof\tfor\tthem;\tthey\tfollow\tonly\tguesses\tand\ttheir\town\tdesires;\twhereas\tthe\t\nguidance\tfrom\ttheir\tLord\thas\tcome\tto\tthem.\t",
    "romanUrduTranslationText": "Woh\tto\tnahi\tmagar\tkuchh\tnām\tke\ttum\tne\taur\ttumhāre\tbāp\tdāda\tne\trakh\tliye\thaiñ\tAllah\tne\tunki\t\nkoi\tsanad\tnahi\tutāri\twoh\tto\tnire\tgumān\taur\tnafs\tki\tkhwahishoñ\tke\tpeechhe\thaiñ\thalāñke\tbe\nshak\t\tunke\tpās\tunke\tRab\tki\ttaraf\tse\thidāyat\tāayi\t"
  },
  {
    "juz": {
      "id": "27"
    },
    "surah": {
      "id": "53"
    },
    "ayatNumber": "24",
    "arabicText": "أَمْ لِلْإِنسَـٰنِ مَا تَمَنَّىٰ",
    "urduTranslationText": "",
    "englishTranslationText": "What!\tWill\tman\tget\twhatever\the\tdreams\tof?\t\t\t",
    "romanUrduTranslationText": "Kya\tādmi\tko\tmil\tjāyega\tjo\tkuch\twoh\tkhayāl\tbāndhe\t"
  },
  {
    "juz": {
      "id": "27"
    },
    "surah": {
      "id": "53"
    },
    "ayatNumber": "25",
    "arabicText": "فَلِلَّهِ ٱلْـَٔاخِرَةُ وَٱلْأُولَىٰ",
    "urduTranslationText": "",
    "englishTranslationText": "So\t(know\tthat)\tAllah\tonly\tis\tthe\tOwner\tof\tall\t-\tthe\tHereafter\tand\tthis\tworld.\t\t",
    "romanUrduTranslationText": "To\tākhirat\taur\tdunya\tsab\tka\tMālik\tAllah\thi\thai\t"
  },
  {
    "juz": {
      "id": "27"
    },
    "surah": {
      "id": "53"
    },
    "ayatNumber": "26",
    "arabicText": "۞ وَكَم مِّن مَّلَكٍۢ فِى ٱلسَّمَـٰوَٰتِ لَا تُغْنِى شَفَـٰعَتُهُمْ شَيْـًٔا إِلَّا مِنۢ بَعْدِ أَن يَأْذَنَ ٱللَّهُ لِمَن يَشَآءُ وَيَرْضَىٰٓ",
    "urduTranslationText": "",
    "englishTranslationText": " And\tmany\tan\tangel\tis\tin\tthe\theavens,\twhose\tintercession\tdoes\tnot\tbenefit\tthe\tleast\tunless\tAllah\t\ngives\tpermission\tfor\twhomever\tHe\twills,\tand\twhom\tHe\tlikes.\t",
    "romanUrduTranslationText": "Aur\tkitne\thi\tfirishte\thaiñ\tāsmānoñ\tmeiñ\tke\tunki\tsifarish\tkuchh\tkām\tnahi\tāti\tmagar\tjabke\tAllah\t\nijazat\tde\tde\tjiske\tliye\tchāhe\taur\tpasand\tfarmaye.\t"
  },
  {
    "juz": {
      "id": "27"
    },
    "surah": {
      "id": "53"
    },
    "ayatNumber": "27",
    "arabicText": "إِنَّ ٱلَّذِينَ لَا يُؤْمِنُونَ بِٱلْـَٔاخِرَةِ لَيُسَمُّونَ ٱلْمَلَـٰٓئِكَةَ تَسْمِيَةَ ٱلْأُنثَىٰ",
    "urduTranslationText": "",
    "englishTranslationText": "Indeed\tthose\twho\tdo\tnot\tbelieve\tin\tthe\t\nHereafter,\tcoin\tthe\tnames\tof\tangels\tlike\t\nthose\tof\tfemales.\t",
    "romanUrduTranslationText": "Be-shak\twoh\tjo\tāakhirat\tpar\tImān\tnahi\t\nrakhte\thaiñ\tmalāika\tka\tnām\taurtoñ\tka\tsa\t\nrakhte\thaiñ"
  },
  {
    "juz": {
      "id": "27"
    },
    "surah": {
      "id": "53"
    },
    "ayatNumber": "28",
    "arabicText": "وَمَا لَهُم بِهِۦ مِنْ عِلْمٍ ۖ إِن يَتَّبِعُونَ إِلَّا ٱلظَّنَّ ۖ وَإِنَّ ٱلظَّنَّ لَا يُغْنِى مِنَ ٱلْحَقِّ شَيْـًۭٔا",
    "urduTranslationText": "",
    "englishTranslationText": "And\tthey\tdo\tnot\thave\tany\tknowledge\tof\tit;\t\nthey\tjust\tfollow\tassumption;\tand\tindeed\t\nassumption\tdoes\tnot\tserve\tany\tpurpose\tin\t\nplace\tof\tthe\tTruth.\t\t",
    "romanUrduTranslationText": "Aur\tunheiñ\tiski\tkuchh\tkhabar\tnahi\twoh\tto\t\nnire\tgumān\tke\tpeechhe\thaiñ\taur\tbe-shak\t\t\ngumān\tyaqeen\tki\tjagah\tkuchh\tkām\tnahi\t\ndeta\t"
  },
  {
    "juz": {
      "id": "27"
    },
    "surah": {
      "id": "53"
    },
    "ayatNumber": "29",
    "arabicText": "فَأَعْرِضْ عَن مَّن تَوَلَّىٰ عَن ذِكْرِنَا وَلَمْ يُرِدْ إِلَّا ٱلْحَيَوٰةَ ٱلدُّنْيَا",
    "urduTranslationText": "",
    "englishTranslationText": "Therefore\tturn\taway\tfrom\twhoever\thas\t\nturned\taway\tfrom\tOur\tremembrance\tand\t\nhas\tdesired\tonly\tthe\tlife\tof\tthis\tworld.\t\t\t",
    "romanUrduTranslationText": "To\ttum\tus\tse\tmoñh\tpher\tlo\tjo\thamāri\tyād\t\nse\tphira\taur\tus\tne\tna\tchāhi\tmagar\tdunya\t\nki\tzindagi"
  },
  {
    "juz": {
      "id": "27"
    },
    "surah": {
      "id": "53"
    },
    "ayatNumber": "30",
    "arabicText": "ذَٰلِكَ مَبْلَغُهُم مِّنَ ٱلْعِلْمِ ۚ إِنَّ رَبَّكَ هُوَ أَعْلَمُ بِمَن ضَلَّ عَن سَبِيلِهِۦ وَهُوَ أَعْلَمُ بِمَنِ ٱهْتَدَىٰ",
    "urduTranslationText": "",
    "englishTranslationText": "This\tis\tthe\textent\tof\ttheir\tknowledge;\t\nindeed\tyour\tLord\twell\tknows\tone\twho\thas\t\nstrayed\tfrom\tHis\tpath,\tand\tHe\twell\tknows\t\none\twho\thas\tattained\tguidance.\t\t",
    "romanUrduTranslationText": "Yahāñ\ttak\tunke\tilm\tki\tpahuñch\thai\tbe\nshak\t\ttumhāra\tRab\tkhoob\tjānta\thai\tjo\tuski\t\nrāh\tse\tbehka\taur\twoh\tkhoob\tjānta\thai\t\njisne\trāh\tpāyi.\t"
  },
  {
    "juz": {
      "id": "27"
    },
    "surah": {
      "id": "53"
    },
    "ayatNumber": "31",
    "arabicText": "وَلِلَّهِ مَا فِى ٱلسَّمَـٰوَٰتِ وَمَا فِى ٱلْأَرْضِ لِيَجْزِىَ ٱلَّذِينَ أَسَـٰٓـُٔوا۟ بِمَا عَمِلُوا۟ وَيَجْزِىَ ٱلَّذِينَ أَحْسَنُوا۟ بِٱلْحُسْنَى",
    "urduTranslationText": "",
    "englishTranslationText": "And\tto\tAllah\tonly\tbelongs\tall\twhatever\tis\t\nin\tthe\theavens\tand\tall\twhatever\tis\tin\tthe\t\nearth,\tin\torder\tto\trepay\tthose\twho\tdo\tevil\t\nfor\twhat\tthey\thave\tdone,\tand\tgive\tan\t\nexcellent\treward\tto\tthose\twho\tdo\tgood.\t\t\t",
    "romanUrduTranslationText": "Aur\tAllah\thi\tka\thai\tjo\tkuch\tāasmānoñ\t\nmeiñ\thai\taur\tjo\tkuchh\tzameen\tmeiñ\ttāke\t\nburāi\tkarne\twaloñ\t\tko\tunke\tkiye\tka\tbadla\t\nde\taur\tneki\tkarne\twaloñ\tko\tnihayat\t\nachcha\tsila\t‘aṭa\tfarmaye.\t"
  },
  {
    "juz": {
      "id": "27"
    },
    "surah": {
      "id": "53"
    },
    "ayatNumber": "32",
    "arabicText": "ٱلَّذِينَ يَجْتَنِبُونَ كَبَـٰٓئِرَ ٱلْإِثْمِ وَٱلْفَوَٰحِشَ إِلَّا ٱللَّمَمَ ۚ إِنَّ رَبَّكَ وَٰسِعُ ٱلْمَغْفِرَةِ ۚ هُوَ أَعْلَمُ بِكُمْ إِذْ أَنشَأَكُم مِّنَ ٱلْأَرْضِ وَإِذْ أَنتُمْ أَجِنَّةٌۭ فِى بُطُونِ أُمَّهَـٰتِكُمْ ۖ فَلَا تُزَكُّوٓا۟ أَنفُسَكُمْ ۖ هُوَ أَعْلَمُ بِمَنِ ٱتَّقَىٰٓ",
    "urduTranslationText": "",
    "englishTranslationText": "Those\twho\tavoid\tthe\tcardinal\tsins\tand\t\nlewdness,\texcept\tthat\tthey\tapproached\tit\t\nand\trefrained;\tindeed\tyour\tLord’s\tmercy\t\nis\tlimitless;\tHe\tknows\tyou\tvery\twell\t–\t\nsince\tHe\thas\tcreated\tyou\tfrom\tclay,\tand\t\nwhen\tyou\twere\tfoetuses\tin\tyour\tmothers’\t\nwombs;\ttherefore\tdo\tnot,\ton\tyour\town,\t\nclaim\tyourselves\tto\tbe\tclean;\tHe\twell\t\nknows\twho\tare\tthe\tpious.\t\t\t",
    "romanUrduTranslationText": "Woh\tjo\tbade\tgunahoñ\t\taur\tbe-hayaiyoñ\tse\t\nbachte\thaiñ\tmagar\titna\tke\tgunah\tke\tpās\t\ngaye\taur\truk\tgaye\tbe-shak\ttumhāre\tRab\tki\t\nmaghfirat\twasee'\thai\twoh\ttumheiñ\t\tkhoob\t\njānta\thai\ttumheiñ\t\tmitti\tse\tpaida\tkiya\taur\t\njab\ttum\tapni\tmā'oñ\tke\tpet\tmeiñ\thamal\t\nthey\tto\tāap\t\tapni\tjānoñ\t\tko\tsuthra\tna\tbatāo\t\nwoh\tkhoob\tjānta\thai\tjo\tparhez-gār\thaiñ\t"
  },
  {
    "juz": {
      "id": "27"
    },
    "surah": {
      "id": "53"
    },
    "ayatNumber": "33",
    "arabicText": "أَفَرَءَيْتَ ٱلَّذِى تَوَلَّىٰ",
    "urduTranslationText": "",
    "englishTranslationText": " So\tdid\tyou\tobserve\thim\twho\tturned\taway?\t",
    "romanUrduTranslationText": " To\tkya\ttum\tne\tdekha\tjo\tphir\tgaya\t"
  },
  {
    "juz": {
      "id": "27"
    },
    "surah": {
      "id": "53"
    },
    "ayatNumber": "34",
    "arabicText": "وَأَعْطَىٰ قَلِيلًۭا وَأَكْدَىٰٓ",
    "urduTranslationText": "",
    "englishTranslationText": "And\the\tgave\ta\tlittle,\tthen\trefrained?\t\t",
    "romanUrduTranslationText": "Aur\tkuchh\tthoda\tsa\tdiya\taur\trok\trakha\t"
  },
  {
    "juz": {
      "id": "27"
    },
    "surah": {
      "id": "53"
    },
    "ayatNumber": "35",
    "arabicText": "أَعِندَهُۥ عِلْمُ ٱلْغَيْبِ فَهُوَ يَرَىٰٓ",
    "urduTranslationText": "",
    "englishTranslationText": "Does\the\thave\tknowledge\tof\tthe\thidden,\tso\the\tcan\tforesee?\t\t",
    "romanUrduTranslationText": "Kya\tuske\tpās\tghaib\tka\tilm\thai\tto\twoh\tdekh\t\nraha\thai\t"
  },
  {
    "juz": {
      "id": "27"
    },
    "surah": {
      "id": "53"
    },
    "ayatNumber": "36",
    "arabicText": "أَمْ لَمْ يُنَبَّأْ بِمَا فِى صُحُفِ مُوسَىٰ",
    "urduTranslationText": "",
    "englishTranslationText": "Did\tnot\tthe\tnews\treach\thim,\tof\tthat\twhich\tis\tmentioned\tin\tthe\tBooks\tof\tMoosa?\t",
    "romanUrduTranslationText": "Kya\tusey\tuski\tkhabar\tna\tāayi\tjo\tsaheefoñ\tmeiñ\thai\tMūsā\tke\t"
  },
  {
    "juz": {
      "id": "27"
    },
    "surah": {
      "id": "53"
    },
    "ayatNumber": "37",
    "arabicText": "وَإِبْرَٰهِيمَ ٱلَّذِى وَفَّىٰٓ",
    "urduTranslationText": "",
    "englishTranslationText": "And\tof\tIbrahim,\twho\twas\tmost\tobedient?\t\t",
    "romanUrduTranslationText": "Aur\tIbraheem\tke\tjo\tahkām\tpoore\tbajā\tlāya\t"
  },
  {
    "juz": {
      "id": "27"
    },
    "surah": {
      "id": "53"
    },
    "ayatNumber": "38",
    "arabicText": "أَلَّا تَزِرُ وَازِرَةٌۭ وِزْرَ أُخْرَىٰ",
    "urduTranslationText": "",
    "englishTranslationText": "That\tno\tburdened\tsoul\tbears\tanother\tsoul’s\tburden?\t\t",
    "romanUrduTranslationText": " Ke\tkoi\tbojh\tuthāne\twāli\tjān\tdoosri\tka\tbojh\tnahi\tuthāti"
  },
  {
    "juz": {
      "id": "27"
    },
    "surah": {
      "id": "53"
    },
    "ayatNumber": "39",
    "arabicText": "وَأَن لَّيْسَ لِلْإِنسَـٰنِ إِلَّا مَا سَعَىٰ",
    "urduTranslationText": "",
    "englishTranslationText": "And\tthat\tman\twill\tnot\tobtain\tanything\texcept\twhat\the\tstrove\tfor?\t\t",
    "romanUrduTranslationText": "Aur\tyeh\tke\tāadmi\tna\tpāayega\tmagar\tapni\tkoshish\t"
  },
  {
    "juz": {
      "id": "27"
    },
    "surah": {
      "id": "53"
    },
    "ayatNumber": "40",
    "arabicText": "وَأَنَّ سَعْيَهُۥ سَوْفَ يُرَىٰ",
    "urduTranslationText": "",
    "englishTranslationText": " And\tthat\this\teffort\twill\tsoon\tbe\tscrutinised?\t\t\t",
    "romanUrduTranslationText": "Aur\tyeh\tke\tuski\tkoshish\t‘an-qareeb\tdekhi\tjāyegi"
  },
  {
    "juz": {
      "id": "27"
    },
    "surah": {
      "id": "53"
    },
    "ayatNumber": "41",
    "arabicText": "ثُمَّ يُجْزَىٰهُ ٱلْجَزَآءَ ٱلْأَوْفَىٰ",
    "urduTranslationText": "",
    "englishTranslationText": "Then\the\twill\tbe\tfully\trepaid\tfor\tit?\t\t",
    "romanUrduTranslationText": "Phir\tuska\tbharpoor\tbadla\tdiya\tjāyega."
  },
  {
    "juz": {
      "id": "27"
    },
    "surah": {
      "id": "53"
    },
    "ayatNumber": "42",
    "arabicText": "وَأَنَّ إِلَىٰ رَبِّكَ ٱلْمُنتَهَىٰ",
    "urduTranslationText": "",
    "englishTranslationText": "And\tthat\tthe\tend\tis\tonly\ttowards\tyour\tLord?\t\t",
    "romanUrduTranslationText": " Aur\tyeh\tke\tbe-shak\t\ttumhāre\tRab\thi\tki\ttaraf\tinteha\thai\t"
  },
  {
    "juz": {
      "id": "27"
    },
    "surah": {
      "id": "53"
    },
    "ayatNumber": "43",
    "arabicText": "وَأَنَّهُۥ هُوَ أَضْحَكَ وَأَبْكَىٰ",
    "urduTranslationText": "",
    "englishTranslationText": "And\tthat\tit\tis\tHe\tWho\tmade\t(you)\tlaugh\tand\tmade\t(you)\tcry?\t",
    "romanUrduTranslationText": "Aur\tyeh\tke\twohi\thai\tjisne\thañsāya\taur\trulāya"
  },
  {
    "juz": {
      "id": "27"
    },
    "surah": {
      "id": "53"
    },
    "ayatNumber": "44",
    "arabicText": "وَأَنَّهُۥ هُوَ أَمَاتَ وَأَحْيَا",
    "urduTranslationText": "",
    "englishTranslationText": " And\tthat\tit\tis\tHe\tWho\tgave\tdeath\tand\tgave\tlife?\t\t",
    "romanUrduTranslationText": "Aur\tyeh\tke\twohi\thai\tjisne\tmāra\taur\tjilāya\t"
  },
  {
    "juz": {
      "id": "27"
    },
    "surah": {
      "id": "53"
    },
    "ayatNumber": "45",
    "arabicText": "وَأَنَّهُۥ خَلَقَ ٱلزَّوْجَيْنِ ٱلذَّكَرَ وَٱلْأُنثَىٰ",
    "urduTranslationText": "",
    "englishTranslationText": "And\tthat\tit\tis\tHe\tWho\thas\tcreated\tthe\t\npairs,\tmale\tand\tfemale?\t\t",
    "romanUrduTranslationText": "Aur\tyeh\tke\tus\tne\tdo\tjode\tbanaye\tnar\taur\t\nmāda\t"
  },
  {
    "juz": {
      "id": "27"
    },
    "surah": {
      "id": "53"
    },
    "ayatNumber": "46",
    "arabicText": "مِن نُّطْفَةٍ إِذَا تُمْنَىٰ",
    "urduTranslationText": "",
    "englishTranslationText": "From\ta\tdrop\tof\tliquid,\twhen\tit\tis\tadded?\t\t",
    "romanUrduTranslationText": " Nutfe\tse\tjab\tdāla\tjāye\t"
  },
  {
    "juz": {
      "id": "27"
    },
    "surah": {
      "id": "53"
    },
    "ayatNumber": "47",
    "arabicText": "وَأَنَّ عَلَيْهِ ٱلنَّشْأَةَ ٱلْأُخْرَىٰ",
    "urduTranslationText": "",
    "englishTranslationText": "And\tthat\tonly\tupon\tHim\tis\tthe\tnext\t\nrevival?\t\t",
    "romanUrduTranslationText": "Aur\tyeh\tke\tusi\tke\tzimme\thai\tpichla\tuthāna\t\t"
  },
  {
    "juz": {
      "id": "27"
    },
    "surah": {
      "id": "53"
    },
    "ayatNumber": "48",
    "arabicText": "وَأَنَّهُۥ هُوَ أَغْنَىٰ وَأَقْنَىٰ",
    "urduTranslationText": "",
    "englishTranslationText": "And\tthat\tit\tis\tHe\tWho\thas\tgiven\twealth\t\nand\tcontentment?\t\t",
    "romanUrduTranslationText": "Aur\tyeh\tke\tusi\tne\tghinā\tdi\taur\tqanā'at\tdi.\t"
  },
  {
    "juz": {
      "id": "27"
    },
    "surah": {
      "id": "53"
    },
    "ayatNumber": "49",
    "arabicText": "وَأَنَّهُۥ هُوَ رَبُّ ٱلشِّعْرَىٰ",
    "urduTranslationText": "",
    "englishTranslationText": " And\tthat\tHe\tonly\tis\tthe\tLord\tof\tthe\tstar\t\nSirius?\t",
    "romanUrduTranslationText": "Aur\tyeh\tke\twohi\tsitāra\tShi’ra\tka\tRab\thai\t"
  },
  {
    "juz": {
      "id": "27"
    },
    "surah": {
      "id": "53"
    },
    "ayatNumber": "50",
    "arabicText": "وَأَنَّهُۥٓ أَهْلَكَ عَادًا ٱلْأُولَىٰ",
    "urduTranslationText": "",
    "englishTranslationText": "And\tthat\tit\tis\tHe\tWho\tearlier\tdestroyed\t\nthe\ttribe\tof\tAad?\t\t",
    "romanUrduTranslationText": "Aur\tyeh\tke\tusi\tne\tpehli\tĀad\tko\thalāk\t\nfarmāya\t"
  },
  {
    "juz": {
      "id": "27"
    },
    "surah": {
      "id": "53"
    },
    "ayatNumber": "51",
    "arabicText": "وَثَمُودَا۟ فَمَآ أَبْقَىٰ",
    "urduTranslationText": "",
    "englishTranslationText": "And\tdestroyed\tthe\ttribe\tof\tThamud,\tnot\t\nsparing\tanyone?\t\t",
    "romanUrduTranslationText": "Aur\tSamood\tko\tto\tkoi\tbāqi\tna\tchorda\t"
  },
  {
    "juz": {
      "id": "27"
    },
    "surah": {
      "id": "53"
    },
    "ayatNumber": "52",
    "arabicText": "وَقَوْمَ نُوحٍۢ مِّن قَبْلُ ۖ إِنَّهُمْ كَانُوا۟ هُمْ أَظْلَمَ وَأَطْغَىٰ",
    "urduTranslationText": "",
    "englishTranslationText": " And\tbefore\tthem,\tthe\tpeople\tof\tNooh?\t\nIndeed\tthey\twere\tmore\tunjust\tand\tmore\t\nrebellious\tthan\tthese!\t\t",
    "romanUrduTranslationText": "Aur\tun\tse\tpehle\tNūh\tki\tqaum\tko\tbe-shak\t\t\nwoh\tun\tse\tbhi\tzālim\taur\tsarkash\tthey\t"
  },
  {
    "juz": {
      "id": "27"
    },
    "surah": {
      "id": "53"
    },
    "ayatNumber": "53",
    "arabicText": "وَٱلْمُؤْتَفِكَةَ أَهْوَىٰ",
    "urduTranslationText": "",
    "englishTranslationText": "And\tthat\tit\tis\tHe\tWho\tthrew\tdown\tthe\t\nupturned\ttownships?\t\t\t",
    "romanUrduTranslationText": "Aur\tusne\tulatne\twāli\tbasti\tko\tneeche\t\ngirāya\t"
  },
  {
    "juz": {
      "id": "27"
    },
    "surah": {
      "id": "53"
    },
    "ayatNumber": "54",
    "arabicText": "فَغَشَّىٰهَا مَا غَشَّىٰ",
    "urduTranslationText": "",
    "englishTranslationText": "So\tthey\twere\tcovered\twith\twhatever\t\ncovered\tthem?\t\t",
    "romanUrduTranslationText": "To\tus\tpar\tchhaya\tjo\tkuch\tchaya\t"
  },
  {
    "juz": {
      "id": "27"
    },
    "surah": {
      "id": "53"
    },
    "ayatNumber": "55",
    "arabicText": "فَبِأَىِّ ءَالَآءِ رَبِّكَ تَتَمَارَىٰ",
    "urduTranslationText": "",
    "englishTranslationText": "So\tO\tlistener!\tWhich\tfavour\tof\tyour\tLord\t\nwill\tyou\tdoubt?\t\t",
    "romanUrduTranslationText": " To\taey\tsunne\twāle!\tApne\tRab\tki\tkaun\tsi\t\nne'matoñ\tmeiñ\tshak\tkarega\t.\t"
  },
  {
    "juz": {
      "id": "27"
    },
    "surah": {
      "id": "53"
    },
    "ayatNumber": "56",
    "arabicText": "هَـٰذَا نَذِيرٌۭ مِّنَ ٱلنُّذُرِ ٱلْأُولَىٰٓ",
    "urduTranslationText": "",
    "englishTranslationText": "He\t(Prophet Muhammad – peace and \nblessings be upon him)\tis\ta\tHerald\tof\t\nWarning,\tlike\tthe\tformer\tHeralds\tof\t\nWarning.\t\t\t",
    "romanUrduTranslationText": "Yeh\tek\tdar\tsunāne\twāle\thaiñ\tagle\tdarāne\t\nwaloñ\t\tki\ttarah\t"
  },
  {
    "juz": {
      "id": "27"
    },
    "surah": {
      "id": "53"
    },
    "ayatNumber": "57",
    "arabicText": "أَزِفَتِ ٱلْـَٔازِفَةُ",
    "urduTranslationText": "",
    "englishTranslationText": "The\tapproaching\tevent\thas\tcome\tnear.\t\t\t",
    "romanUrduTranslationText": " Pās\tāayi\tpās\tāne\twāli\t"
  },
  {
    "juz": {
      "id": "27"
    },
    "surah": {
      "id": "53"
    },
    "ayatNumber": "58",
    "arabicText": "لَيْسَ لَهَا مِن دُونِ ٱللَّهِ كَاشِفَةٌ",
    "urduTranslationText": "",
    "englishTranslationText": "None\texcept\tAllah\tcan\tavert\tit.\t\t\t\t",
    "romanUrduTranslationText": "Allah\tke\tsiwa\tuska\tkoi\tkholne\twāla\tnahi"
  },
  {
    "juz": {
      "id": "27"
    },
    "surah": {
      "id": "53"
    },
    "ayatNumber": "59",
    "arabicText": "أَفَمِنْ هَـٰذَا ٱلْحَدِيثِ تَعْجَبُونَ",
    "urduTranslationText": "",
    "englishTranslationText": " So\tare\tyou\tsurprised\tat\tthis\tfact?\t\t\t\t",
    "romanUrduTranslationText": "To\tkya\tis\tbāt\tse\ttum\tt’ajjub\tkarte\tho\t\t"
  },
  {
    "juz": {
      "id": "27"
    },
    "surah": {
      "id": "53"
    },
    "ayatNumber": "60",
    "arabicText": "وَتَضْحَكُونَ وَلَا تَبْكُونَ",
    "urduTranslationText": "",
    "englishTranslationText": "And\tyou\tlaugh,\tand\tdo\tnot\tweep!\t\t\t\t\t",
    "romanUrduTranslationText": "Aur\thanste\tho\taur\trote\tnahi.\t"
  },
  {
    "juz": {
      "id": "27"
    },
    "surah": {
      "id": "53"
    },
    "ayatNumber": "61",
    "arabicText": "وَأَنتُمْ سَـٰمِدُونَ",
    "urduTranslationText": "",
    "englishTranslationText": "And\tyou\tare\tlost\tin\tplay!\t\t\t\t\t",
    "romanUrduTranslationText": "Aur\ttum\tkhel\tmeiñ\tpade\tho.\t"
  },
  {
    "juz": {
      "id": "27"
    },
    "surah": {
      "id": "53"
    },
    "ayatNumber": "62",
    "arabicText": "فَٱسْجُدُوا۟ لِلَّهِ وَٱعْبُدُوا۟ ۩",
    "urduTranslationText": "",
    "englishTranslationText": "Therefore\tprostrate\tfor\tAllah,\tand\tworship\tHim.\t(Command\tof\tProstration\t#\t12)\t\t\t\t",
    "romanUrduTranslationText": "To\tAllah\tke\tliye\tsajda\taur\tuski\tbandagi\t\nkaro.\t(Sajde\tka\thukm\t#\t12)\t"
  },
  {
    "juz": {
      "id": "27"
    },
    "surah": {
      "id": "54"
    },
    "ayatNumber": "1",
    "arabicText": "ٱقْتَرَبَتِ ٱلسَّاعَةُ وَٱنشَقَّ ٱلْقَمَرُ",
    "urduTranslationText": "",
    "englishTranslationText": "The\tLast\tDay\tcame\tnear,\tand\tthe\tmoon\tsplit\tapart.\t\t",
    "romanUrduTranslationText": "Pās\tāayi\tQiyamat\taur\tshaq\tho\tgaya\tchānd\t"
  },
  {
    "juz": {
      "id": "27"
    },
    "surah": {
      "id": "54"
    },
    "ayatNumber": "2",
    "arabicText": "وَإِن يَرَوْا۟ ءَايَةًۭ يُعْرِضُوا۟ وَيَقُولُوا۟ سِحْرٌۭ مُّسْتَمِرٌّۭ",
    "urduTranslationText": "",
    "englishTranslationText": "And\twhen\tthey\tsee\ta\tsign,\tthey\tturn\taway\tand\tsay,\t“Just\ta\tcustomary\tmagic!”\t\t",
    "romanUrduTranslationText": "Aur\tagar\tdekheiñ\tkoi\tnishāni\tto\tmuñh\tpherte\taur\tkehte\thaiñ\tyeh\tto\tjādu\thai\tchala\tāta\t"
  },
  {
    "juz": {
      "id": "27"
    },
    "surah": {
      "id": "54"
    },
    "ayatNumber": "3",
    "arabicText": "وَكَذَّبُوا۟ وَٱتَّبَعُوٓا۟ أَهْوَآءَهُمْ ۚ وَكُلُّ أَمْرٍۢ مُّسْتَقِرٌّۭ",
    "urduTranslationText": "",
    "englishTranslationText": "And\tthey\tdenied\tand\tfollowed\ttheir\town\tdesires,\twhereas\teach\tmatter\thas\tbeen\tdecided!\t\t",
    "romanUrduTranslationText": "Aur\tunhoñ\tne\tjhutlāya\taur\tapni\tkhwahishoñ\tke\tpeeche\thuwe\taur\thar\tkām\tqarār\tpa\tchuka\thai"
  },
  {
    "juz": {
      "id": "27"
    },
    "surah": {
      "id": "54"
    },
    "ayatNumber": "4",
    "arabicText": "وَلَقَدْ جَآءَهُم مِّنَ ٱلْأَنۢبَآءِ مَا فِيهِ مُزْدَجَرٌ",
    "urduTranslationText": "",
    "englishTranslationText": " And\tindeed\tthe\tnews\twhich\thad\ta\tlot\tof\tdeterrence,\tcame\tto\tthem.\t\t",
    "romanUrduTranslationText": "Aur\tbe-shak\tunke\tpās\twoh\tkhabreiñ\tāyiñ\tjin\tmeiñ\tkāfi\trok\tthi\t"
  },
  {
    "juz": {
      "id": "27"
    },
    "surah": {
      "id": "54"
    },
    "ayatNumber": "5",
    "arabicText": "حِكْمَةٌۢ بَـٰلِغَةٌۭ ۖ فَمَا تُغْنِ ٱلنُّذُرُ",
    "urduTranslationText": "",
    "englishTranslationText": "The\tpinnacle\tof\twisdom\t–\tso\thow\twill\tthe\tHeralds\tof\twarning\tprovide\tany\tbenefit?\t\t",
    "romanUrduTranslationText": "Inteha\tko\tpahuñchi\thuyi\thikmat\tphir\tkya\tkām\tdeiñ\tdar\tsunāne\twāle.\t\t"
  },
  {
    "juz": {
      "id": "27"
    },
    "surah": {
      "id": "54"
    },
    "ayatNumber": "6",
    "arabicText": "فَتَوَلَّ عَنْهُمْ ۘ يَوْمَ يَدْعُ ٱلدَّاعِ إِلَىٰ شَىْءٍۢ نُّكُرٍ",
    "urduTranslationText": "",
    "englishTranslationText": "Therefore\tturn\taway\tfrom\tthem;\ton\tthe\tday\twhen\tthe\tannouncer\twill\tcall\ttowards\ta\tsevere\t\nunknown\tmatter\t–\t\t",
    "romanUrduTranslationText": "To\ttum\tun\tse\tmuñh\tpher\tlo\tjis\tdin\tbulāne\twāla\tek\tsakht\tbe\tpehchāni\tbāt\tki\ttaraf\tbulayega\t\t\t"
  },
  {
    "juz": {
      "id": "27"
    },
    "surah": {
      "id": "54"
    },
    "ayatNumber": "7",
    "arabicText": "خُشَّعًا أَبْصَـٰرُهُمْ يَخْرُجُونَ مِنَ ٱلْأَجْدَاثِ كَأَنَّهُمْ جَرَادٌۭ مُّنتَشِرٌۭ",
    "urduTranslationText": "",
    "englishTranslationText": "They\twill\tcome\tout\tfrom\tthe\tgraves\twith\t\neyes\tlowered,\tas\tif\tthey\twere\tspread\tlocusts.",
    "romanUrduTranslationText": "Neechi\tāñkheiñ\tkiye\thuwe\tqabroñ\tse\tnikleñ\t\nge\tgoya\twoh\ttedi\t(Tiddi)\thaiñ\tphaili\thuyi\t\t"
  },
  {
    "juz": {
      "id": "27"
    },
    "surah": {
      "id": "54"
    },
    "ayatNumber": "8",
    "arabicText": "مُّهْطِعِينَ إِلَى ٱلدَّاعِ ۖ يَقُولُ ٱلْكَـٰفِرُونَ هَـٰذَا يَوْمٌ عَسِرٌۭ",
    "urduTranslationText": "",
    "englishTranslationText": "Rushing\ttowards\tthe\tcaller;\tthe\t\ndisbelievers\twill\tsay,\t“This\tis\ta\ttough\tday.”\t",
    "romanUrduTranslationText": "Bulāne\twāle\tki\ttaraf\tlapakte\thuwe\tkāfir\t\nkaheñ\tge\tyeh\tdin\tsakht\thai.\t"
  },
  {
    "juz": {
      "id": "27"
    },
    "surah": {
      "id": "54"
    },
    "ayatNumber": "9",
    "arabicText": "۞ كَذَّبَتْ قَبْلَهُمْ قَوْمُ نُوحٍۢ فَكَذَّبُوا۟ عَبْدَنَا وَقَالُوا۟ مَجْنُونٌۭ وَٱزْدُجِرَ",
    "urduTranslationText": "",
    "englishTranslationText": "Before\tthese,\tthe\tpeople\tof\tNooh\tdenied\t\nand\tthey\tbelied\tOur\tbondman\tand\tsaid,\t\n“He\tis\ta\tmadman”\tand\trebuffed\thim.",
    "romanUrduTranslationText": "In\tse\tpehle\tNūh\tki\tqaum\tne\tjhutlāya\tto\t\nhamāre\tbande\tko\tjhoota\tbataya\taur\tbole\t\nwoh\tmajnoon\thai\taur\tusey\tjhidka\t"
  },
  {
    "juz": {
      "id": "27"
    },
    "surah": {
      "id": "54"
    },
    "ayatNumber": "10",
    "arabicText": "فَدَعَا رَبَّهُۥٓ أَنِّى مَغْلُوبٌۭ فَٱنتَصِرْ",
    "urduTranslationText": "",
    "englishTranslationText": "He\ttherefore\tprayed\tto\this\tLord,\t“I\tam\t\noverpowered,\ttherefore\tavenge\tme.”\t\t",
    "romanUrduTranslationText": "To\tus\tne\tapne\tRab\tse\tdu’a\tki\tke\tmaiñ\t\nmaghloob\thuñ\ttu\tmera\tbadla\tle\t.\t"
  }
]